{"client":"Thunder Client","collectionName":"valex","dateExported":"2022-07-12T12:55:10.313Z","version":"1.1","folders":[],"requests":[{"_id":"d9623bdb-e013-4515-838d-8c58d3157c79","colId":"10f1853f-382f-4d74-a6de-59c804db3166","containerId":"","name":"{{url}}:4000/newCard","url":"{{url}}:4000/newCard","method":"POST","sortNum":10000,"created":"2022-07-12T12:53:46.758Z","modified":"2022-07-12T12:53:46.758Z","headers":[{"name":"x-api-key","value":"zadKLNx.DzvOVjQH01TumGl2urPjPQSxUbf67vs0"}],"params":[],"body":{"type":"json","raw":"{\n    \"type\":\"education\",\n    \"employeeId\":2\n}","form":[]},"tests":[]},{"_id":"4c33c2bc-bc37-4732-a720-fe88cc62e48f","colId":"10f1853f-382f-4d74-a6de-59c804db3166","containerId":"","name":"{{url}}:4000/activateCard","url":"{{url}}:4000/activateCard","method":"POST","sortNum":20000,"created":"2022-07-12T12:53:56.016Z","modified":"2022-07-12T12:53:56.016Z","headers":[],"params":[],"body":{"type":"json","raw":"{\n\n    \"password\":\"4444\",\n    \"cardNumber\": \"6372-7803-1965-7262\",\n    \"cvc\":\"048\"\n} ","form":[]},"tests":[]},{"_id":"7e6693bd-7eaa-4494-8aa3-de57dd33893e","colId":"10f1853f-382f-4d74-a6de-59c804db3166","containerId":"","name":"{{url}}:4000/blockCard","url":"{{url}}:4000/blockCard","method":"POST","sortNum":30000,"created":"2022-07-12T12:54:06.872Z","modified":"2022-07-12T12:54:06.873Z","headers":[],"params":[],"body":{"type":"json","raw":"{\n    \"cardId\": 1,\n    \"password\":\"4444\"\n}","form":[]},"tests":[]},{"_id":"ea90ca12-7295-4715-9d1b-b3a71a28a3a1","colId":"10f1853f-382f-4d74-a6de-59c804db3166","containerId":"","name":"{{url}}:4000/unblockCard","url":"{{url}}:4000/unblockCard","method":"POST","sortNum":40000,"created":"2022-07-12T12:54:20.577Z","modified":"2022-07-12T12:54:20.577Z","headers":[],"params":[],"body":{"type":"json","raw":"{\n    \"cardId\": 1,\n    \"password\":\"4444\"\n}","form":[]},"tests":[]},{"_id":"29505461-c39f-4d45-b73f-443eaf3891ee","colId":"10f1853f-382f-4d74-a6de-59c804db3166","containerId":"","name":"{{url}}:4000/recharge","url":"{{url}}:4000/recharge","method":"POST","sortNum":50000,"created":"2022-07-12T12:54:34.456Z","modified":"2022-07-12T12:54:34.456Z","headers":[{"name":"x-api-key","value":"zadKLNx.DzvOVjQH01TumGl2urPjPQSxUbf67vs0"}],"params":[],"body":{"type":"json","raw":"{\n    \"amount\":5000,\n    \"cardId\": 3\n}","form":[]},"tests":[]},{"_id":"fb7803ff-d9bb-425d-bcec-3d1ff3453f54","colId":"10f1853f-382f-4d74-a6de-59c804db3166","containerId":"","name":"{{url}}:4000/purchases","url":"{{url}}:4000/purchases","method":"POST","sortNum":60000,"created":"2022-07-12T12:54:51.153Z","modified":"2022-07-12T12:54:51.153Z","headers":[],"params":[],"body":{"type":"json","raw":"{\n    \"cardId\":3,\n    \"amount\":5,\n    \"password\":\"4444\",\n    \"businessId\":1\n}","form":[]},"tests":[]},{"_id":"b66ae855-e4aa-4a10-b1e2-c841b7ce5893","colId":"10f1853f-382f-4d74-a6de-59c804db3166","containerId":"","name":"{{url}}:4000/extract/3","url":"{{url}}:4000/extract/3","method":"GET","sortNum":70000,"created":"2022-07-12T12:55:01.401Z","modified":"2022-07-12T12:55:01.401Z","headers":[],"params":[],"body":{"type":"json","raw":"{\n    \n    \"amount\":5,\n    \"password\":\"4444\",\n    \"businessId\":1\n}","form":[]},"tests":[]}]}
